cuequivariance/VERSION
cuequivariance/__init__.py
cuequivariance/etc/linalg.py
cuequivariance/etc/permutations.py
cuequivariance/etc/sympy_utils.py
cuequivariance/group_theory/__init__.py
cuequivariance/group_theory/equivariant_polynomial.py
cuequivariance/group_theory/equivariant_tensor_product.py
cuequivariance/group_theory/descriptors/__init__.py
cuequivariance/group_theory/descriptors/irreps_tp.py
cuequivariance/group_theory/descriptors/rotations.py
cuequivariance/group_theory/descriptors/spherical_harmonics_.py
cuequivariance/group_theory/descriptors/symmetric_contractions.py
cuequivariance/group_theory/descriptors/transposition.py
cuequivariance/group_theory/experimental/__init__.py
cuequivariance/group_theory/experimental/e3nn.py
cuequivariance/group_theory/experimental/escn.py
cuequivariance/group_theory/experimental/gatr.py
cuequivariance/group_theory/experimental/mace/__init__.py
cuequivariance/group_theory/experimental/mace/symmetric_contractions.py
cuequivariance/group_theory/irreps_array/__init__.py
cuequivariance/group_theory/irreps_array/context_decorator.py
cuequivariance/group_theory/irreps_array/context_irrep_class.py
cuequivariance/group_theory/irreps_array/context_layout.py
cuequivariance/group_theory/irreps_array/irrep_utils.py
cuequivariance/group_theory/irreps_array/irreps.py
cuequivariance/group_theory/irreps_array/irreps_and_layout.py
cuequivariance/group_theory/irreps_array/irreps_layout.py
cuequivariance/group_theory/irreps_array/misc_ui.py
cuequivariance/group_theory/irreps_array/numpy_irreps_array.py
cuequivariance/group_theory/irreps_array/reduced_tensor_product.py
cuequivariance/group_theory/representations/__init__.py
cuequivariance/group_theory/representations/irrep.py
cuequivariance/group_theory/representations/irrep_o3.py
cuequivariance/group_theory/representations/irrep_so3.py
cuequivariance/group_theory/representations/irrep_su2.py
cuequivariance/group_theory/representations/rep.py
cuequivariance-0.8.1.dist-info/METADATA
cuequivariance-0.8.1.dist-info/WHEEL
cuequivariance-0.8.1.dist-info/licenses/LICENSE
cuequivariance-0.8.1.dist-info/RECORD
