Metadata-Version: 2.4
Name: cuequivariance
Version: 0.8.1
Summary: CUDA accelerated equivariant operations
Author: NVIDIA Corporation
License: 
License-File: LICENSE
Classifier: Intended Audience :: Developers
Classifier: Programming Language :: Python
Classifier: Programming Language :: Python :: 3.10
Classifier: Programming Language :: Python :: 3.11
Classifier: Programming Language :: Python :: 3.12
Requires-Python: >=3.10
Requires-Dist: networkx
Requires-Dist: numpy
Requires-Dist: opt-einsum
Requires-Dist: scipy
Requires-Dist: sympy
